smarttext/__init__.py
smarttext/analyzer.py
smarttext/language_detect.py
smarttext/sentiment.py
smarttext/visualize.py
smarttext-0.1.0.dist-info/licenses/LICENSE
tests/__init__.py
tests/test_analyzer.py
smarttext-0.1.0.dist-info/METADATA
smarttext-0.1.0.dist-info/WHEEL
smarttext-0.1.0.dist-info/top_level.txt
smarttext-0.1.0.dist-info/RECORD
