Metadata-Version: 2.4
Name: smarttext
Version: 0.1.0
Summary: An intelligent text analysis library for Python
Home-page: https://github.com/eldar-eliyev/smarttext
Author: Eldar Eliyev
Author-email: eldar@example.com
Classifier: Programming Language :: Python :: 3
Classifier: License :: OSI Approved :: MIT License
Classifier: Operating System :: OS Independent
Classifier: Topic :: Text Processing :: Linguistic
Requires-Python: >=3.8
License-File: LICENSE
Requires-Dist: langdetect
Requires-Dist: textblob
Requires-Dist: matplotlib
Dynamic: author
Dynamic: author-email
Dynamic: classifier
Dynamic: description
Dynamic: description-content-type
Dynamic: home-page
Dynamic: license-file
Dynamic: requires-dist
Dynamic: requires-python
Dynamic: summary
